MANIFEST.in
README.rst
setup.py
py_labeler/__init__.py
py_labeler.egg-info/PKG-INFO
py_labeler.egg-info/SOURCES.txt
py_labeler.egg-info/dependency_links.txt
py_labeler.egg-info/not-zip-safe
py_labeler.egg-info/requires.txt
py_labeler.egg-info/top_level.txt
py_labeler/labeler/__init__.py
py_labeler/labeler/labeler.py
py_labeler/labeler/controller/FilterController.py
py_labeler/labeler/controller/LabelUpdateController.py
py_labeler/labeler/controller/StatsController.py
py_labeler/labeler/controller/TuplePairDisplayController.py
py_labeler/labeler/controller/__init__.py
py_labeler/labeler/view/Renderer.py
py_labeler/labeler/view/__init__.py
py_labeler/labeler/view/js/main_window.js
py_labeler/labeler/view/templates/common_css.html
py_labeler/labeler/view/templates/common_js.html
py_labeler/labeler/view/templates/dummy_page.html
py_labeler/labeler/view/templates/horizontal_layout.html
py_labeler/labeler/view/templates/menu_bar.html
py_labeler/labeler/view/templates/options.html
py_labeler/labeler/view/templates/pagination.html
py_labeler/labeler/view/templates/single_layout.html
py_labeler/labeler/view/templates/tuple_pair.html
py_labeler/labeler/view/templates/vertical_layout.html
py_labeler/tests/__init__.py
py_labeler/tests/test_labeler.py
py_labeler/tests/test_labeler_workflow.py
py_labeler/tests/test_datasets/A.csv
py_labeler/tests/test_datasets/A.metadata
py_labeler/tests/test_datasets/B.csv
py_labeler/tests/test_datasets/C.csv
py_labeler/tests/test_datasets/C.metadata
py_labeler/tests/test_datasets/C1.csv
py_labeler/tests/test_datasets/C1.metadata
py_labeler/tests/test_datasets/__init__.py
py_labeler/tests/test_datasets/labeled_data_demo.csv
py_labeler/tests/test_datasets/labeled_data_demo.metadata
py_labeler/tests/test_datasets/restA.csv
py_labeler/tests/test_datasets/restB.csv
py_labeler/utils/ApplicationContext.py
py_labeler/utils/__init__.py
py_labeler/utils/generic_helper.py
py_labeler/utils/validation_helper.py